[
{
    "model": "chiton_runway.basic",
    "fields": {
        "name": "Black camisole",
        "slug": "black-camisole",
        "category": [
            "shirts"
        ],
        "primary_color": [
            "black"
        ],
        "secondary_colors": []
    }
},
{
    "model": "chiton_runway.basic",
    "fields": {
        "name": "Black cardigan",
        "slug": "black-cardigan",
        "category": [
            "overshirts"
        ],
        "primary_color": [
            "black"
        ],
        "secondary_colors": []
    }
},
{
    "model": "chiton_runway.basic",
    "fields": {
        "name": "Black leggings",
        "slug": "black-leggings",
        "category": [
            "pants"
        ],
        "primary_color": [
            "black"
        ],
        "secondary_colors": []
    }
},
{
    "model": "chiton_runway.basic",
    "fields": {
        "name": "Black pants",
        "slug": "black-pants",
        "category": [
            "pants"
        ],
        "primary_color": [
            "black"
        ],
        "secondary_colors": []
    }
},
{
    "model": "chiton_runway.basic",
    "fields": {
        "name": "Black shell",
        "slug": "black-shell",
        "category": [
            "shirts"
        ],
        "primary_color": [
            "black"
        ],
        "secondary_colors": []
    }
},
{
    "model": "chiton_runway.basic",
    "fields": {
        "name": "Black skirt",
        "slug": "black-skirt",
        "category": [
            "skirts"
        ],
        "primary_color": [
            "black"
        ],
        "secondary_colors": []
    }
},
{
    "model": "chiton_runway.basic",
    "fields": {
        "name": "Black sweater",
        "slug": "black-sweater",
        "category": [
            "shirts"
        ],
        "primary_color": [
            "black"
        ],
        "secondary_colors": []
    }
},
{
    "model": "chiton_runway.basic",
    "fields": {
        "name": "Black tights",
        "slug": "black-tights",
        "category": [
            "hosiery"
        ],
        "primary_color": [
            "black"
        ],
        "secondary_colors": []
    }
},
{
    "model": "chiton_runway.basic",
    "fields": {
        "name": "Black T-shirt",
        "slug": "black-t-shirt",
        "category": [
            "shirts"
        ],
        "primary_color": [
            "black"
        ],
        "secondary_colors": []
    }
},
{
    "model": "chiton_runway.basic",
    "fields": {
        "name": "Casual black blazer",
        "slug": "casual-black-blazer",
        "category": [
            "overshirts"
        ],
        "primary_color": [
            "black"
        ],
        "secondary_colors": []
    }
},
{
    "model": "chiton_runway.basic",
    "fields": {
        "name": "Casual black dress",
        "slug": "casual-black-dress",
        "category": [
            "dresses"
        ],
        "primary_color": [
            "black"
        ],
        "secondary_colors": []
    }
},
{
    "model": "chiton_runway.basic",
    "fields": {
        "name": "Dark jeans",
        "slug": "dark-jeans",
        "category": [
            "pants"
        ],
        "primary_color": null,
        "secondary_colors": []
    }
},
{
    "model": "chiton_runway.basic",
    "fields": {
        "name": "Formal black blazer",
        "slug": "formal-black-blazer",
        "category": [
            "overshirts"
        ],
        "primary_color": [
            "black"
        ],
        "secondary_colors": []
    }
},
{
    "model": "chiton_runway.basic",
    "fields": {
        "name": "Formal black dress",
        "slug": "formal-black-dress",
        "category": [
            "dresses"
        ],
        "primary_color": [
            "black"
        ],
        "secondary_colors": []
    }
},
{
    "model": "chiton_runway.basic",
    "fields": {
        "name": "Khakis",
        "slug": "khakis",
        "category": [
            "pants"
        ],
        "primary_color": null,
        "secondary_colors": []
    }
},
{
    "model": "chiton_runway.basic",
    "fields": {
        "name": "Nude pantyhose",
        "slug": "nude-pantyhose",
        "category": [
            "hosiery"
        ],
        "primary_color": null,
        "secondary_colors": []
    }
},
{
    "model": "chiton_runway.basic",
    "fields": {
        "name": "Skirt",
        "slug": "skirt",
        "category": [
            "skirts"
        ],
        "primary_color": null,
        "secondary_colors": []
    }
},
{
    "model": "chiton_runway.basic",
    "fields": {
        "name": "Tunic",
        "slug": "tunic",
        "category": [
            "shirts"
        ],
        "primary_color": null,
        "secondary_colors": []
    }
},
{
    "model": "chiton_runway.basic",
    "fields": {
        "name": "White button-down",
        "slug": "white-button-down",
        "category": [
            "shirts"
        ],
        "primary_color": [
            "white"
        ],
        "secondary_colors": []
    }
},
{
    "model": "chiton_runway.basic",
    "fields": {
        "name": "White camisole",
        "slug": "white-camisole",
        "category": [
            "shirts"
        ],
        "primary_color": [
            "white"
        ],
        "secondary_colors": []
    }
},
{
    "model": "chiton_runway.basic",
    "fields": {
        "name": "White shell",
        "slug": "white-shell",
        "category": [
            "shirts"
        ],
        "primary_color": [
            "white"
        ],
        "secondary_colors": []
    }
}
]
